turing_transforms/cross_correlate.py
turing_transforms/transpose.py
turing_transforms/window.py
turing_transforms2-0.1.2.dist-info/METADATA
turing_transforms2-0.1.2.dist-info/WHEEL
turing_transforms2-0.1.2.dist-info/RECORD
