Metadata-Version: 2.1
Name: turing-transforms2
Version: 0.1.2
Summary: Utility transform functions for casual data engineer.
License: MIT
Author: John van Doe
Requires-Python: >=3.10,<3.13
Classifier: License :: OSI Approved :: MIT License
Classifier: Programming Language :: Python :: 3
Classifier: Programming Language :: Python :: 3.10
Classifier: Programming Language :: Python :: 3.11
Requires-Dist: numpy (>=1.26.0,<2.0.0)
